README.rst
setup.py
bin/nsc-delete-user
bin/nsc-engine-pools
bin/nsc-exporter
bin/nsc-janitor
bin/nsc-make-exporter-privileges
bin/nsc-remove-old-reports
bin/nsc-remove-old-sites
bin/nsc-users
extras/nexpose-exporter.env
extras/nexpose-exporter.service
extras/nexpose-janitor.env
extras/nexpose-janitor.service
nexpose/__init__.py
nexpose/args.py
nexpose/get_credentials.py
nexpose/logging.py
nexpose/nexpose.py
nexpose_py.egg-info/PKG-INFO
nexpose_py.egg-info/SOURCES.txt
nexpose_py.egg-info/dependency_links.txt
nexpose_py.egg-info/requires.txt
nexpose_py.egg-info/top_level.txt